LICENSE
MANIFEST.in
README.rst
setup.py
zeversolar_api/__init__.py
zeversolar_api/exceptions.py
zeversolar_api.egg-info/PKG-INFO
zeversolar_api.egg-info/SOURCES.txt
zeversolar_api.egg-info/dependency_links.txt
zeversolar_api.egg-info/requires.txt
zeversolar_api.egg-info/top_level.txt
zeversolar_api.egg-info/zip-safe